open_hh_models/__init__.py
open_hh_models/models.py
ohh_pydantic-0.1.1.dist-info/METADATA
ohh_pydantic-0.1.1.dist-info/WHEEL
ohh_pydantic-0.1.1.dist-info/RECORD
