Metadata-Version: 2.4
Name: ohh-pydantic
Version: 0.1.1
Summary: Implementation of the Open Hand History Spec in Pydantic
Project-URL: Homepage, https://github.com/allansatt/ohh_pydantic
Project-URL: Issues, https://github.com/allansatt/ohh_pydantic/issues
Author-email: Allan Sattelberg Rivera <allansattriv@gmail.com>
License-Expression: MIT
Classifier: Operating System :: OS Independent
Classifier: Programming Language :: Python :: 3
Requires-Python: >=3.9
Requires-Dist: pydantic>=2.12.5
